LICENSE
MANIFEST.in
README.rst
requirements.txt
setup.py
bkyototycoon/__init__.py
bkyototycoon/client.c
bkyototycoon/client.pyx
python_kyototycoon_binary.egg-info/PKG-INFO
python_kyototycoon_binary.egg-info/SOURCES.txt
python_kyototycoon_binary.egg-info/dependency_links.txt
python_kyototycoon_binary.egg-info/requires.txt
python_kyototycoon_binary.egg-info/top_level.txt
tests/__init__.py
tests/test_client.py