Metadata-Version: 1.1
Name: python-kyototycoon-binary
Version: 0.1.1
Summary: A Python client for accessing Kyoto Tycoon via binary protocol
Home-page: http://github.com/studio-ousia/python-kyototycoon-binary
Author: Studio Ousia
Author-email: admin@ousia.jp
License: Copyright 2013 Studio Ousia
